pyformation/__init__.py
pyformation/helpers.py
pyformation/render.py
pyformation/resources.py
pyformation/settings.py
pyformation/setup_questions.py
pyformation/bin/__init__.py
pyformation/bin/pyformation_admin.py
pyformation/bin/refresh_specifications.py
pyformation/templates/.env
pyformation/templates/.env.production
pyformation/templates/.env.rspec
pyformation/templates/.env.test
pyformation/templates/.gitignore
pyformation/templates/__init__.py
pyformation/templates/ecsstack.py
pyformation/templates/parentstack.py
pyformation/templates/vpcstack.py
pyformation/utils/__init__.py
pyformation/utils/deploy_utils.py
pyformation/utils/get_aws_data.py
pyformation/utils/hash_url.py
pyformation-0.1.4.dist-info/METADATA
pyformation-0.1.4.dist-info/WHEEL
pyformation-0.1.4.dist-info/entry_points.txt
pyformation-0.1.4.dist-info/top_level.txt
pyformation-0.1.4.dist-info/RECORD
