Metadata-Version: 2.1
Name: pyformation
Version: 0.1.4
Summary: CloudFormation eloquently expressed as Python
Home-page: http://github.com/dennisvink/pyformation
Author: Dennis Vink
Author-email: dennis@drvink.com
License: MIT
Platform: UNKNOWN
Requires-Dist: requests
Requires-Dist: beautifulsoup4
Requires-Dist: pyfiglet
Requires-Dist: PyInquirer
Requires-Dist: lxml
Requires-Dist: jinja2
Requires-Dist: GitPython
Requires-Dist: python-dotenv
Requires-Dist: moto
